{
    "AddObsDetails": {
        "Add": {
            "translation": "Dodaj",
            "notes": ""
        },
        "HideHelptext": {
            "translation": "Skrij pomoč",
            "notes": ""
        }
    },
    "AppearanceName": {
        "translation": "Izgled:",
        "notes": ""
    },
    "Attachment": {
        "Attachment": {
            "translation": "Priponka",
            "notes": ""
        },
        "DropzoneText": {
            "translation": "Povlecite in spustite datoteke za prenos ali kliknite, da izberete.",
            "notes": ""
        },
        "InvalidAttachmentType": {
            "translation": "Neveljavna priloga. Dovoljene vrste datotek so:",
            "notes": ""
        },
        "NoDescription": {
            "translation": "Brez opisa",
            "notes": ""
        },
        "Uploading": {
            "translation": "Nalaganje",
            "notes": ""
        }
    },
    "Cancel": {
        "translation": "Prekliči",
        "notes": ""
    },
    "ChangePassword": {
        "translation": "Spremeni geslo",
        "notes": ""
    },
    "Chip": {
        "GoToObservation": {
            "translation": "Pojdi na opažanje",
            "notes": ""
        },
        "ShowAllObservations": {
            "translation": "Pokaži vse",
            "notes": ""
        }
    },
    "COMPASS_DIRECTION": {
        "EAST": {
            "translation": "Vzhod",
            "notes": ""
        },
        "EAST_SHORT": {
            "translation": "V",
            "notes": ""
        },
        "NORTH": {
            "translation": "Sever",
            "notes": ""
        },
        "NORTH_EAST": {
            "translation": "Severovzhod",
            "notes": ""
        },
        "NORTH_EAST_SHORT": {
            "translation": "SV",
            "notes": ""
        },
        "NORTH_SHORT": {
            "translation": "S",
            "notes": ""
        },
        "NORTH_WEST": {
            "translation": "Severozahod",
            "notes": ""
        },
        "NORTH_WEST_SHORT": {
            "translation": "SZ",
            "notes": ""
        },
        "SOUTH": {
            "translation": "Jug",
            "notes": ""
        },
        "SOUTH_EAST": {
            "translation": "Jugovzhod",
            "notes": ""
        },
        "SOUTH_EAST_SHORT": {
            "translation": "JV",
            "notes": ""
        },
        "SOUTH_SHORT": {
            "translation": "J",
            "notes": ""
        },
        "SOUTH_WEST": {
            "translation": "Jugozahod",
            "notes": ""
        },
        "SOUTH_WEST_SHORT": {
            "translation": "JZ",
            "notes": ""
        },
        "WEST": {
            "translation": "Zahod",
            "notes": ""
        },
        "WEST_SHORT": {
            "translation": "Z",
            "notes": ""
        }
    },
    "Cookies": {
        "AboutUseFirstParagraph": {
            "translation": "Regobs uporablja piškotke za izboljšanje vaše uporabniške izkušnje, ko obiščete spletno stran. Piškotek je besedilna datoteka, ki se med obiskom ali ob interakciji s spletno stranjo vstavi v notranji pomnilnik vašega brskalnika.",
            "notes": ""
        },
        "AboutUseSecondParagraph": {
            "translation": "Osnova za to je 6. člen (1) (f) Pravilnika o zasebnosti, ki nam omogoča obdelavo informacij, ki so potrebne za zaščito interesa, ki odtehta zasebnost posameznikov. Ta interes je dobro delovanje strani, ki vam omogoča dobro uporabniško izkušnjo.",
            "notes": ""
        },
        "AboutUseThirdParagraph": {
            "translation": "Regobs ne uporablja piškotkov za beleženje vzorcev uporabe posameznih uporabnikov ali drugih informacij, ki bi lahko kršile njihovo zasebnost.",
            "notes": ""
        },
        "CookiesDescription": {
            "translation": "V spodnji tabeli navajamo, katere piškotke uporablja beta.regobs.no, kateri podatki se shranjujejo in zakaj jih spletna stran potrebuje.",
            "notes": ""
        },
        "Customize": {
            "translation": "Prilagodi",
            "notes": ""
        },
        "CustomizeDescription": {
            "translation": "Večina sodobnih brskalnikov (Google Chrome, Internet Explorer, Firefox, Safari, Opera itd.) je nastavljena tako, da samodejno sprejemajo piškotke, vendar lahko spremenite svoje nastavitve tako, da piškotki ne bodo sprejeti. Upoštevajte, da to lahko povzroči, da regobs.no ne bo deloval optimalno.",
            "notes": ""
        },
        "DataProcessorColumnLabel": {
            "translation": "Obdelovalec podatkov",
            "notes": ""
        },
        "DescriptionColumnLabel": {
            "translation": "Opis",
            "notes": ""
        },
        "Descriptions": {
            "__utma": {
                "translation": "Uporablja se za razločevanje uporabnikov in sej.",
                "notes": ""
            },
            "__utmb": {
                "translation": "Uporablja se za določanje novih sej/obiskov.",
                "notes": ""
            },
            "__utmc": {
                "translation": "Uporablja se pri določanju novih sej/obiskov.",
                "notes": ""
            },
            "__utmt": {
                "translation": "Uporablja se za zmanjšanje števila zahtev.",
                "notes": ""
            },
            "__utmz": {
                "translation": "Uporablja se za shranjevanje, kako je uporabnik prišel na stran.",
                "notes": ""
            }
        },
        "DomainColumnLabel": {
            "translation": "Domena",
            "notes": ""
        },
        "HowToAdminister": {
            "translation": "pojasni, kako lahko sami upravljate piškotke.",
            "notes": ""
        },
        "Label": {
            "translation": "Piškotki",
            "notes": ""
        },
        "NameColumnLabel": {
            "translation": "Piškotek",
            "notes": ""
        },
        "TheWebsite": {
            "translation": "Spletna stran",
            "notes": ""
        },
        "Title": {
            "translation": "Uporaba piškotkov",
            "notes": ""
        }
    },
    "CopiedToClipboard": {
        "translation": "Povezava do opažanja skopirana v odložišče.",
        "notes": ""
    },
    "CountOf": {
        "translation": "Število",
        "notes": ""
    },
    "CreateAccount": {
        "translation": "Ustvari NVE-račun",
        "notes": ""
    },
    "CreateObservation": {
        "translation": "Ustvari opažanje",
        "notes": ""
    },
    "Date": {
        "translation": "Datum",
        "notes": ""
    },
    "Delete": {
        "translation": "Izbriši",
        "notes": ""
    },
    "Dialogs": {
        "Account": {
            "LoggedOutDescription": {
                "translation": "Samodejno ste bili odjavljeni. Ali se želite ponovno prijaviti?",
                "notes": ""
            },
            "LoggedOutTitle": {
                "translation": "Odjavljeni",
                "notes": ""
            }
        },
        "Buttons": {
            "AddForm": {
                "translation": "Shrani",
                "notes": ""
            },
            "Back": {
                "translation": "Nazaj",
                "notes": ""
            },
            "Next": {
                "translation": "OK",
                "notes": ""
            }
        },
        "Location": {
            "Description": {
                "translation": "Na zemljevidu označite, kje je bilo opravljeno opažanje. Poiščite lokacijo z iskanjem ali s pomočjo tipk plus (+) in minus (-).",
                "notes": ""
            },
            "DescriptionMobile": {
                "translation": "Na zemljevidu označite, kje je bilo opravljeno opažanje.",
                "notes": ""
            },
            "EditName": {
                "translation": "Nastavite ime lokacije",
                "notes": ""
            },
            "EditNameLabel": {
                "translation": "Ime lokacije",
                "notes": ""
            },
            "Title": {
                "translation": "Kje je bilo opravljeno opažanje?",
                "notes": ""
            }
        },
        "NickName": {
            "Create": {
                "HelpText": {
                    "translation": "Za uporabo Varsom Regobs potrebujete uporabniško ime. Uporabniško ime je prikazano na vaših opažanjih.",
                    "notes": ""
                },
                "Title": {
                    "translation": "Dodajte uporabniško ime",
                    "notes": ""
                }
            },
            "Edit": {
                "HelpText": {
                    "translation": "Uporabniško ime je prikazano na vaših opažanjih.",
                    "notes": ""
                },
                "Title": {
                    "translation": "Uredite uporabniško ime",
                    "notes": ""
                }
            },
            "Error": {
                "Error": {
                    "translation": "Uporabniškega imena ni bilo mogoče shraniti. Poskusite pozneje.",
                    "notes": ""
                },
                "Invalid": {
                    "translation": "Prosimo vnesite uporabniško ime",
                    "notes": ""
                }
            },
            "InputText": {
                "translation": "Prosimo vnesite uporabniško ime",
                "notes": ""
            }
        },
        "SaveSearch": {
            "Description": {
                "translation": "Iskanje bo shranjeno v brskalniku in ne bo sinhronizirano med napravami. Shranite lahko največ 5 iskanj glede na tip naravne grožnje.",
                "notes": ""
            },
            "DialogTitle": {
                "translation": "Shrani iskanje",
                "notes": ""
            },
            "ExpansionPanelTitle": {
                "translation": "Shranjena iskanja",
                "notes": ""
            },
            "FailedSave": {
                "translation": "Iskanja ni bilo mogoče shraniti",
                "notes": ""
            },
            "InputLabel": {
                "translation": "Išči po imenu",
                "notes": ""
            },
            "SaveButton": {
                "translation": "Shrani iskanje",
                "notes": ""
            }
        },
        "Time": {
            "AdditionalInformation": {
                "translation": "Dodatne informacije",
                "notes": ""
            },
            "Description": {
                "translation": "Vnesite čas opažanja. Uporabite lokalni čas na mestu opažanja.",
                "notes": ""
            },
            "Exact": {
                "translation": "Natančno",
                "notes": ""
            },
            "MoreThanOneKm": {
                "translation": "Več kot 1 km",
                "notes": ""
            },
            "NotMemberOfAnyGroups": {
                "translation": "Niste član nobene skupine",
                "notes": ""
            },
            "Share": {
                "translation": "Delite s skupino",
                "notes": ""
            },
            "Source": {
                "translation": "Vir",
                "notes": ""
            },
            "Title": {
                "translation": "Kdaj je bilo opravljeno opažanje?",
                "notes": ""
            },
            "Uncertainty": {
                "translation": "Negotovo določen položaj",
                "notes": ""
            }
        }
    },
    "Direction": {
        "E": {
            "translation": "V",
            "notes": ""
        },
        "N": {
            "translation": "S",
            "notes": ""
        },
        "NE": {
            "translation": "SV",
            "notes": ""
        },
        "NW": {
            "translation": "SZ",
            "notes": ""
        },
        "S": {
            "translation": "J",
            "notes": ""
        },
        "SE": {
            "translation": "JV",
            "notes": ""
        },
        "SW": {
            "translation": "JZ",
            "notes": ""
        },
        "W": {
            "translation": "Z",
            "notes": ""
        }
    },
    "Email": {
        "translation": "E-pošta",
        "notes": ""
    },
    "Footer": {
        "AboutDataInRegObs": {
            "translation": "O podatkih v regObs",
            "notes": ""
        },
        "AboutRegObsHeader": {
            "translation": "O Regobs",
            "notes": ""
        },
        "BeAwareThat": {
            "translation": "Prosimo, upoštevajte, da je nujne stvari najbolje sporočiti neposredno ali v Facebook skupini.",
            "notes": ""
        },
        "Collaboration": {
            "translation": "Sodelovanje",
            "notes": ""
        },
        "ConditionOfUse": {
            "translation": "Pogoji uporabe",
            "notes": ""
        },
        "ContactIndividual": {
            "translation": "Stopite v stik s posamezno službo za opozarjanje, ki najbolj ustreza temu, za kar uporabljate regObs.",
            "notes": ""
        },
        "ContactUsHeader": {
            "translation": "Pišite nam",
            "notes": ""
        },
        "FeedbackForm1": {
            "translation": "Uporabite lahko tudi ",
            "notes": ""
        },
        "FeedbackForm2": {
            "translation": "obrazec za povratne informacije",
            "notes": ""
        },
        "FeedbackForm3": {
            "translation": " za sporočanje povratnih informacij o tej storitvi.",
            "notes": ""
        },
        "GoTo": {
            "translation": "Pojdi na",
            "notes": ""
        },
        "HearFromYou": {
            "translation": "Veseli bomo vaših izkušenj pri uporabi regObs ali strokovnih poizvedb.",
            "notes": ""
        },
        "IskartAbout": {
            "translation": "Preberite opozorila o ledu, ki jih pripravlja NVE na podlagi razpoložljivih informacij o ledu in vremenskih razmerah.",
            "notes": ""
        },
        "IskartAlt": {
            "translation": "Logotip za Iskart.no",
            "notes": ""
        },
        "NveVarsom": {
            "translation": "Opozorila o plazovih in poplavah na NVE so del več orodij, ki smo jih vzpostavili skupaj z varsom.no.",
            "notes": ""
        },
        "OtherToolsHeader": {
            "translation": "Druga orodja",
            "notes": ""
        },
        "ReadMoreAboutRegobs": {
            "translation": "Več o regObs",
            "notes": ""
        },
        "RegObsContactEmail": {
            "translation": "Kontaktepost@regobs.no",
            "notes": ""
        },
        "RegObsCovers": {
            "translation": "Zajema opozorila o snežnih padavinah, ledu, snežnih plazovih in poplavah.",
            "notes": ""
        },
        "RegObsFacebook": {
            "translation": "Strokovna skupina regObs na Facebooku",
            "notes": ""
        },
        "RegObsGatheringPlace": {
            "translation": "regObs je zbirališče za opažanja in dogodkov, ki se uporabljajo za opozarjanje in pripravljenost na izredne razmere.",
            "notes": ""
        },
        "SeNorgeAbout": {
            "translation": "seNorge je odprt spletni portal, na katerem so prikazani podosobljeni zemljevidi snežnih, vremenskih in vodnih razmer ter podnebja na Norveškem.",
            "notes": ""
        },
        "SeNorgeAlt": {
            "translation": "Logotip za Senorge.no",
            "notes": ""
        },
        "VarsomAbout": {
            "translation": "Varsom.no je storitev, ki jo zagotavlja NVE v sodelovanju z Meteorološkim inštitutom, Norveško upravo za javne ceste in Bane NOR.",
            "notes": ""
        },
        "VarsomAlt": {
            "translation": "Logotip za Varsom.no",
            "notes": ""
        },
        "XGeoAbout": {
            "translation": "xGeo je orodje, ki se uporablja za opozarjanje na izredne razmere in spremljanje ter opozarjanje na poplave, zemeljske in snežne plazove.",
            "notes": ""
        },
        "XGeoAlt": {
            "translation": "Logotip za Xgeo.no",
            "notes": ""
        }
    },
    "Forgotten": {
        "translation": "Pozabljeno geslo?",
        "notes": ""
    },
    "from": {
        "translation": "od",
        "notes": ""
    },
    "Geohazards": {
        "All": {
            "translation": "Vse",
            "notes": ""
        },
        "Ice": {
            "translation": "Led",
            "notes": ""
        },
        "Snow": {
            "translation": "Sneg",
            "notes": ""
        },
        "Soil": {
            "translation": "Tla",
            "notes": ""
        },
        "Water": {
            "translation": "Voda",
            "notes": ""
        },
        "WaterSoil": {
            "translation": "Voda in tla",
            "notes": ""
        }
    },
    "GeoLocation": {
        "PositionError": {
            "PermissionDenied": {
                "translation": "Če želite pridobiti svoj položaj, morate spremeniti nastavitve brskalnika",
                "notes": ""
            },
            "PositionUnavailable": {
                "translation": "Ne moremo pridobiti vašega položaja",
                "notes": ""
            },
            "Timeout": {
                "translation": "Pridobivanje vašega položaja je trajalo predolgo",
                "notes": ""
            }
        }
    },
    "GoBack": {
        "translation": "Pojdi nazaj",
        "notes": ""
    },
    "GoToObservation": {
        "translation": "Pojdi na opažanje",
        "notes": ""
    },
    "GoToReportPage": {
        "translation": "Pojdi na ogled poročil",
        "notes": ""
    },
    "HeightKey": {
        "translation": "Višina",
        "notes": ""
    },
    "Home": {
        "translation": "Domov",
        "notes": ""
    },
    "HomeLocationSearch": {
        "All": {
            "translation": "Vse",
            "notes": ""
        },
        "Change": {
            "translation": "Uredi",
            "notes": ""
        },
        "Days": {
            "translation": "dnevi",
            "notes": ""
        },
        "Last": {
            "translation": "Zadnji",
            "notes": ""
        },
        "NoMaps": {
            "translation": "Ni podpornega zemljevida",
            "notes": ""
        },
        "Search": {
            "translation": "Iskanje na zemljevidu",
            "notes": ""
        }
    },
    "Information": {
        "translation": "Informacije",
        "notes": ""
    },
    "InvalidDate": {
        "translation": "Neveljaven datum",
        "notes": ""
    },
    "is": {
        "translation": "led",
        "notes": ""
    },
    "jord": {
        "translation": "zemeljski plaz",
        "notes": ""
    },
    "LanguageLabel": {
        "translation": "Jezik:",
        "notes": ""
    },
    "Login": {
        "CreateNewRegObsUser": {
            "translation": "Tu ustvarite regObs uporabnika",
            "notes": ""
        },
        "EmailRequired": {
            "translation": "Vnesite svoj e-poštni naslov.",
            "notes": ""
        },
        "NoUser": {
            "translation": "Niste uporabnik?",
            "notes": ""
        },
        "PasswordRequired": {
            "translation": "Vnesite geslo.",
            "notes": ""
        },
        "ValidEmail": {
            "translation": "Vnesite veljaven e-poštni naslov.",
            "notes": ""
        }
    },
    "Map": {
        "InMapView": {
            "translation": "na zemljevidu",
            "notes": ""
        },
        "Loading": {
            "translation": "Nalaganje",
            "notes": ""
        },
        "LoadingObservations": {
            "translation": "Nalaganje opažanj",
            "notes": ""
        }
    },
    "MapMode": {
        "translation": "Zemljevid",
        "notes": ""
    },
    "MapSelection": {
        "Ice": {
            "Channel": {
                "translation": "Kanal",
                "notes": ""
            },
            "FracturedIceAlongShore": {
                "translation": "Počen led ob obali",
                "notes": ""
            },
            "OftenDangerousIceConditions": {
                "translation": "Pogosto nevarni pogoji na ledu",
                "notes": ""
            },
            "Penstock": {
                "translation": "Cevovod",
                "notes": ""
            },
            "PowerPlantTunnel": {
                "translation": "Predor elektrarne",
                "notes": ""
            },
            "SignificantlyWeakenedIce": {
                "translation": "Znatno oslabljen led",
                "notes": ""
            },
            "WeakenedIce": {
                "translation": "Oslabljen led",
                "notes": ""
            }
        },
        "Observations": {
            "translation": "Opažanja",
            "notes": ""
        },
        "ObservationsAndSupportMaps": {
            "translation": "Opažanja in podporni zemljevidi",
            "notes": ""
        },
        "Opacity": {
            "translation": "Prosojnost",
            "notes": ""
        },
        "SnowWarningRegions": {
            "translation": "Opozorilna območja",
            "notes": ""
        },
        "Soil": {
            "HighLoose": {
                "translation": "Visoko (območje sproščanja)",
                "notes": ""
            },
            "HighOutlet": {
                "translation": "Visoko (območje odlaganja)",
                "notes": ""
            },
            "LowLoose": {
                "translation": "Nizko (območje sproščanja)",
                "notes": ""
            },
            "LowOutlet": {
                "translation": "Nizko (območje odlaganja)",
                "notes": ""
            },
            "MappedAreas": {
                "translation": "Kartirana območja",
                "notes": ""
            },
            "MediumLoose": {
                "translation": "Srednje (območje sproščanja)",
                "notes": ""
            },
            "MediumOutlet": {
                "translation": "Srednje (območje odlaganja)",
                "notes": ""
            },
            "None": {
                "translation": "Brez",
                "notes": ""
            },
            "PotentialHazards": {
                "translation": "Možne nevarnosti",
                "notes": ""
            }
        },
        "SupportClayZonesDescription": {
            "translation": "Območja hitre gline",
            "notes": ""
        },
        "SupportClayZonesName": {
            "translation": "Območja hitre gline",
            "notes": ""
        },
        "SupportFloodZonesDescription": {
            "translation": "Poplavna območja",
            "notes": ""
        },
        "SupportFloodZonesName": {
            "translation": "Poplavna območja",
            "notes": ""
        },
        "SupportMap": {
            "translation": "Podporni zemljevid: ",
            "notes": ""
        },
        "SupportMaps": {
            "translation": "Podporni zemljevidi",
            "notes": ""
        },
        "SupportSteepnessDescription": {
            "translation": "Barve označujejo naklon terena v stopinjah",
            "notes": ""
        },
        "SupportSteepnessName": {
            "translation": "Naklon",
            "notes": ""
        },
        "SupportWeakenedIceDescription": {
            "translation": "Podporni zemljevid prikazuje dele vodotokov, ki se pozimi obnašajo nepredvidljivo zaradi proizvodnje električne energije.",
            "notes": ""
        },
        "SupportWeakenedIceName": {
            "translation": "Oslabljen led",
            "notes": ""
        },
        "Water": {
            "1000YearFlood": {
                "translation": "1000-letna poplava",
                "notes": ""
            },
            "100YearFlood": {
                "translation": "100-letna poplava",
                "notes": ""
            },
            "10YearFlood": {
                "translation": "10-letna poplava",
                "notes": ""
            },
            "200YearFlood": {
                "translation": "200-letna poplava",
                "notes": ""
            },
            "200YearFloodClimate": {
                "translation": "200-letna poplava (podnebje)",
                "notes": ""
            },
            "20YearFlood": {
                "translation": "20-letna poplava",
                "notes": ""
            },
            "500YearFlood": {
                "translation": "500-letna poplava",
                "notes": ""
            },
            "50YearFlood": {
                "translation": "50-letna poplava",
                "notes": ""
            },
            "AjourRecognized": {
                "translation": "Posodobljeno",
                "notes": ""
            },
            "Current": {
                "translation": "Trenutno",
                "notes": ""
            },
            "ForReview": {
                "translation": "Za pregled",
                "notes": ""
            },
            "LowPoint": {
                "translation": "Poplavljena nizka točka na:",
                "notes": ""
            },
            "RiverAndWater10YearFlood": {
                "translation": "Reka in voda 10-letna poplava",
                "notes": ""
            },
            "UnderPlanning": {
                "translation": "V načrtovanju",
                "notes": ""
            }
        }
    },
    "MapSideNav": {
        "ChosenObservation": {
            "translation": "Izbrano opažanje",
            "notes": ""
        },
        "Hide": {
            "translation": "Skrij",
            "notes": ""
        },
        "MapSelection": {
            "translation": "Izbira zemljevida",
            "notes": ""
        },
        "MoveMap": {
            "translation": "Povečaj območje ali razširi časovno obdobje za prikaz več opažanj",
            "notes": ""
        },
        "NoObservationsInMapView": {
            "translation": "Ni opažanj na zemljevidu.",
            "notes": ""
        },
        "Observations": {
            "translation": "Opažanja",
            "notes": ""
        },
        "ObservationsInMapView": {
            "translation": "Opažanja na zemljevidu",
            "notes": ""
        },
        "Options": {
            "translation": "Možnosti",
            "notes": ""
        },
        "ShowInList": {
            "translation": "Prikaži na seznamu",
            "notes": ""
        },
        "ShowMapSelection": {
            "translation": "Prikaži izbiro zemljevida",
            "notes": ""
        },
        "ShowObservationsInMapView": {
            "translation": "Prikaži opažanja na zemljevidu",
            "notes": ""
        }
    },
    "Menu": {
        "translation": "Menu",
        "notes": ""
    },
    "metersOverSeaLevel": {
        "translation": "metrov nadmorske višine",
        "notes": ""
    },
    "MultipleRegistrations": {
        "translation": "vnosi",
        "notes": ""
    },
    "MyPage": {
        "MyCompetence": {
            "translation": "Moja usposobljenost",
            "notes": ""
        },
        "MyGroups": {
            "translation": "Moje skupine",
            "notes": ""
        },
        "MyObservations": {
            "Competence": {
                "translation": "Usposobljenost",
                "notes": ""
            },
            "ContactQuestion": {
                "translation": "Če imate kakršnakoli vprašanja glede usposobljenosti, nas kontaktirajte.",
                "notes": ""
            },
            "HighestCompetence": {
                "translation": "NAJVIŠJA USPOSOBLJENOST",
                "notes": ""
            },
            "MyCompetences": {
                "translation": "Moje usposobljenosti",
                "notes": ""
            },
            "MyNveAccount": {
                "translation": "Moj NVE-račun",
                "notes": ""
            },
            "NoCompetence": {
                "translation": "Vašemu Regobs uporabniku niste dodali informacij o usposobljenosti.",
                "notes": ""
            },
            "NoObservations": {
                "Message": {
                    "translation": "Vnesli niste še nobenega opažanja. Ko boste z vnosom opažanja zabeležili, kar vidite na prostem, bo to vidno tukaj.",
                    "notes": ""
                },
                "Title": {
                    "translation": "Delite, kar vidite!",
                    "notes": ""
                }
            },
            "Title": {
                "translation": "Moja opažanja",
                "notes": ""
            },
            "UnknownCompetence": {
                "translation": "NEZNANA USPOSOBLJENOST",
                "notes": ""
            }
        },
        "MyPage": {
            "translation": "Moja stran",
            "notes": ""
        },
        "MyPlaces": {
            "translation": "Moji kraji",
            "notes": ""
        },
        "UserInfo": {
            "EditNickname": {
                "translation": "Uredite uporabniško ime",
                "notes": ""
            }
        },
        "VarsomUser": {
            "translation": "Varsom uporabnik",
            "notes": ""
        }
    },
    "Navbar": {
        "All": {
            "ObservationsFromLastSevenDays": {
                "translation": "Prikaži vsa opažanja zadnjih 7 dni",
                "notes": ""
            }
        },
        "Ice": {
            "RegisterObservation": {
                "translation": "Novo opažanje ledu",
                "notes": ""
            },
            "SearchInObservation": {
                "translation": "Poročila o ledu",
                "notes": ""
            },
            "ShowObservationsInMap": {
                "translation": "Opažanja ledu in zemljevid oslabljenega ledu",
                "notes": ""
            }
        },
        "RegisterObservation": {
            "translation": "Vnesi opažanje",
            "notes": ""
        },
        "SearchInObservation": {
            "translation": "Išči med opažanji",
            "notes": ""
        },
        "ShowObservationsInMap": {
            "translation": "Prikaži opažanja na zemljevidu",
            "notes": ""
        },
        "Snow": {
            "RegisterObservation": {
                "translation": "Novo opažanje snega",
                "notes": ""
            },
            "SearchInObservation": {
                "translation": "Poročila o snegu",
                "notes": ""
            },
            "ShowObservationsInMap": {
                "translation": "Opažanja snega in zemljevid naklona",
                "notes": ""
            }
        },
        "Soil": {
            "RegisterObservation": {
                "translation": "Novo opažanje tal",
                "notes": ""
            },
            "SearchInObservation": {
                "translation": "Poročila o vodi in tleh",
                "notes": ""
            },
            "ShowObservationsInMap": {
                "translation": "Opažanja zemlje in tal ter zemeljski plazovi",
                "notes": ""
            }
        },
        "Water": {
            "RegisterObservation": {
                "translation": "Novo opažanje vode",
                "notes": ""
            },
            "SearchInObservation": {
                "translation": "Poročila o vodi in tleh",
                "notes": ""
            },
            "ShowObservationsInMap": {
                "translation": "Opažanja vode in tal ter zemljevid poplavnih območij",
                "notes": ""
            }
        }
    },
    "No": {
        "translation": "Ne",
        "notes": ""
    },
    "Now": {
        "translation": "zdaj",
        "notes": ""
    },
    "NveAccountSignIn": {
        "translation": "Vpis",
        "notes": ""
    },
    "observation": {
        "translation": " opažanja",
        "notes": ""
    },
    "ObservationCard": {
        "AboveSeaLevel": {
            "translation": "M.N.V.",
            "notes": ""
        },
        "Download": {
            "translation": "Prenos",
            "notes": ""
        },
        "ForecastRegion": {
            "translation": "Opozorilno območje",
            "notes": ""
        },
        "Forms": {
            "translation": "Obrazci",
            "notes": ""
        },
        "Observed": {
            "translation": "Opaženo:",
            "notes": ""
        },
        "ObsId": {
            "translation": "ID:",
            "notes": ""
        },
        "Original": {
            "translation": "Prikaži izvirnik",
            "notes": ""
        },
        "Registered": {
            "translation": "Vnešeno:",
            "notes": ""
        },
        "SentInBy": {
            "translation": "Objavil",
            "notes": ""
        },
        "Updated": {
            "translation": "Posodobljeno:",
            "notes": ""
        }
    },
    "observations": {
        "translation": "opažanje/a",
        "notes": ""
    },
    "Observations": {
        "AvalancheActivityObs": {
            "Aspect": {
                "translation": "Orientacija pobočja",
                "notes": ""
            },
            "AvalancheTID": {
                "translation": "Vrsta",
                "notes": ""
            },
            "AvalancheTriggerTID": {
                "translation": "Sprožilec",
                "notes": ""
            },
            "Comment": {
                "translation": "Komentar",
                "notes": ""
            },
            "DateWarning": {
                "translation": "Datum se razlikuje od časa opažanja",
                "notes": ""
            },
            "DtAvalancheTime": {
                "translation": "Čas",
                "notes": ""
            },
            "DuringTheDay": {
                "translation": "Čez dan",
                "notes": ""
            },
            "EstimatedTime": {
                "translation": "Ocenjen časovni okvir",
                "notes": ""
            },
            "HeigthStartZone": {
                "translation": "Višina cone proženja",
                "notes": ""
            },
            "HowManyAvalanches": {
                "translation": "Število plazov",
                "notes": ""
            },
            "MetersOverSeaLevel": {
                "translation": "metrov nadmorske višine",
                "notes": ""
            },
            "NoAvalancheActivity": {
                "translation": "Ni opažene plazovne aktivnosti",
                "notes": ""
            },
            "NumberAndSize": {
                "translation": "Število in velikost",
                "notes": ""
            },
            "ObsName": {
                "translation": "Plazovna aktivnost",
                "notes": ""
            }
        },
        "AvalancheActivityObs2": {
            "AvalancheTID": {
                "translation": "Vrsta",
                "notes": ""
            },
            "Comment": {
                "translation": "Komentar",
                "notes": ""
            },
            "DtAvalancheTime": {
                "translation": "Čas",
                "notes": ""
            },
            "MetersOverSeaLevel": {
                "translation": "metrov nadmorske višine",
                "notes": ""
            },
            "NumberAndSizeAndTrigger": {
                "translation": "Število, velikost in sprožilec",
                "notes": ""
            },
            "ObsName": {
                "translation": "Plazovna aktivnost",
                "notes": ""
            },
            "Prevalence": {
                "translation": "Razširjenost",
                "notes": ""
            }
        },
        "AvalancheDangerObs": {
            "Comment": {
                "translation": "Komentar",
                "notes": ""
            },
            "DangerSignTID": {
                "translation": "Vrsta",
                "notes": ""
            },
            "ObsName": {
                "translation": "Opažanje nevarnosti za snežni plaz",
                "notes": ""
            }
        },
        "AvalancheEvalProblem2": {
            "AvalancheExtTID": {
                "translation": "Vrsta",
                "notes": ""
            },
            "AvalCauseAttributeLightTID": {
                "translation": "Neugodne značilnosti šibke plasti",
                "notes": ""
            },
            "AvalCauseDepthTID": {
                "translation": "Višina snežne odeje med šibko plastjo in površjem",
                "notes": ""
            },
            "AvalCauseTID": {
                "translation": "Vrsta šibke plasti",
                "notes": ""
            },
            "AvalProbabilityTID": {
                "translation": "Verjetnost za plaz",
                "notes": ""
            },
            "AvalTriggerSimpleTID": {
                "translation": "Pričakovana obremenitev, ki bi sprožila plaz",
                "notes": ""
            },
            "Comment": {
                "translation": "Comment",
                "notes": ""
            },
            "DestructiveSizeTID": {
                "translation": "Pričakovana velikost plazu",
                "notes": ""
            },
            "ObsName": {
                "translation": "Ocena plazovnega problema",
                "notes": ""
            },
            "PrevalenceArea": {
                "translation": "Razširjenost problema",
                "notes": ""
            }
        },
        "AvalancheEvaluation": {
            "AvalancheDangerTID": {
                "translation": "Stopnja nevarnosti",
                "notes": ""
            },
            "AvalancheDevelopment": {
                "translation": "Razvoj",
                "notes": ""
            },
            "AvalancheEvaluation1": {
                "translation": "Ocena",
                "notes": ""
            },
            "AvalancheProblemTID1": {
                "translation": "Plazovni problem 1",
                "notes": ""
            },
            "AvalancheProblemTID2": {
                "translation": "Plazovni problem 2",
                "notes": ""
            },
            "AvalancheProblemTID3": {
                "translation": "Plazovni problem 3",
                "notes": ""
            },
            "Comment": {
                "translation": "Komentar plazovne napovedi",
                "notes": ""
            },
            "Evaluation": {
                "translation": "Ocena nevarnosti",
                "notes": ""
            },
            "ForecastCorrect": {
                "translation": "Ocena plazovne napovedi na varsom.no",
                "notes": ""
            },
            "ObsName": {
                "translation": "Ocena nevarnosti plazov",
                "notes": ""
            },
            "ValidExposition": {
                "translation": "Izpostavljenost",
                "notes": ""
            }
        },
        "AvalancheEvaluation2": {
            "AvalancheDangerTID": {
                "translation": "Stopnja nevarnosti",
                "notes": ""
            },
            "AvalancheDevelopment": {
                "translation": "Razvoj",
                "notes": ""
            },
            "AvalancheEvaluation": {
                "translation": "Ocena",
                "notes": ""
            },
            "AvalancheProblem": {
                "translation": "Plazovni problem",
                "notes": ""
            },
            "ExposedTerrain": {
                "translation": "Izpostavljen teren",
                "notes": ""
            },
            "ObsName": {
                "translation": "Ocena nevarnosti plazov",
                "notes": ""
            }
        },
        "AvalancheEvaluation3": {
            "AvalancheDangerTID": {
                "translation": "Stopnja nevarnosti",
                "notes": ""
            },
            "AvalancheDevelopment": {
                "translation": "Razvoj",
                "notes": ""
            },
            "AvalancheEvaluation": {
                "translation": "Ocena",
                "notes": ""
            },
            "ForecastComment": {
                "translation": "Komentar",
                "notes": ""
            },
            "ForecastCorrectTID": {
                "translation": "Pravilnost napovedi",
                "notes": ""
            },
            "ObsName": {
                "translation": "Ocena nevarnosti plazov",
                "notes": ""
            }
        },
        "AvalancheObs": {
            "AvalancheTID": {
                "translation": "Vrsta",
                "notes": ""
            },
            "AvalancheTriggerTID": {
                "translation": "Sprožilec plazu",
                "notes": ""
            },
            "AvalancheType": {
                "translation": "Tip plazu",
                "notes": ""
            },
            "AvalCauseTID": {
                "translation": "Šibka plast",
                "notes": ""
            },
            "Comment": {
                "translation": "Komentar",
                "notes": ""
            },
            "DestructiveSizeTID": {
                "translation": "Velikost",
                "notes": ""
            },
            "DtAvalancheTime": {
                "translation": "Čas sprožitve (obvezno)",
                "notes": ""
            },
            "FractureHeight": {
                "translation": "Višina napoke (cm)",
                "notes": ""
            },
            "FractureWidth": {
                "translation": "Širina napoke (m)",
                "notes": ""
            },
            "HeigthStartZone": {
                "translation": "Območje začetka",
                "notes": ""
            },
            "HeigthStopZone": {
                "translation": "Območje konca",
                "notes": ""
            },
            "IncidentDescription": {
                "translation": "Nesreča ali poškodba",
                "notes": ""
            },
            "IncidentPlaceholder": {
                "translation": "Je plaz povzročil kakšno škodo, nesrečo ali skorajšnjo nesrečo? Zakaj in kako se je zgodil? Se bi bilo situaciji mogoče izogniti?",
                "notes": ""
            },
            "ObsName": {
                "translation": "Opažanje plazu",
                "notes": ""
            },
            "Position": {
                "translation": "Lokacija plazu",
                "notes": ""
            },
            "PositionDescription": {
                "translation": "Določite začetno in končno točko plazu.",
                "notes": ""
            },
            "SetStartPosition": {
                "translation": "Določite začetno točko",
                "notes": ""
            },
            "SetStopPosition": {
                "translation": "Določite končno točko",
                "notes": ""
            },
            "TerrainStartZoneTID": {
                "translation": "Tip terena na območju proženja",
                "notes": ""
            },
            "TrajectoryName": {
                "translation": "Pot plazu",
                "notes": ""
            },
            "ValidExposition": {
                "translation": "Izpostavljenost",
                "notes": ""
            }
        },
        "AvalancheProblem": {
            "AvalancheDestructiveSize": {
                "translation": "Pričakovana velikost plazu",
                "notes": ""
            },
            "AvalancheProbability": {
                "translation": "Možnost proženja snežnih plazov",
                "notes": ""
            },
            "AvalancheTriggerProbability": {
                "translation": "Stabilnost snežne odeje",
                "notes": ""
            },
            "AvalancheType": {
                "translation": "Tip plazu",
                "notes": ""
            },
            "Comment": {
                "translation": "Komentar",
                "notes": ""
            },
            "NoWeakLayers": {
                "translation": "Ni šibkih plasti",
                "notes": ""
            },
            "Propagation": {
                "translation": "Prostorska porazdelitev",
                "notes": ""
            },
            "WeakLayer": {
                "translation": "Šibka plast",
                "notes": ""
            },
            "WeakLayerDepth": {
                "translation": "Globina šibke plasti",
                "notes": ""
            }
        },
        "CompressionTest": {
            "Comment": {
                "translation": "Komentar",
                "notes": ""
            },
            "DistanceFromTop": {
                "translation": "Oddaljenost od vrha (cm)",
                "notes": ""
            },
            "FractureType": {
                "translation": "Tip razpoke",
                "notes": ""
            },
            "Include": {
                "translation": "Vključi v snežni profil",
                "notes": ""
            },
            "NumberOfHits": {
                "translation": "Število udarcev",
                "notes": ""
            },
            "ObsName": {
                "translation": "Tlačni test",
                "notes": ""
            },
            "Stability": {
                "translation": "Stabilnost",
                "notes": ""
            },
            "StabilityEvalTID": {
                "translation": "Stabilnost",
                "notes": ""
            },
            "Test": {
                "translation": "Test",
                "notes": ""
            },
            "Type": {
                "translation": "Tip testa",
                "notes": ""
            }
        },
        "DamageObs": {
            "Comment": {
                "translation": "Komentar",
                "notes": ""
            },
            "DamageTypeTID": {
                "translation": "Vrsta",
                "notes": ""
            },
            "LocationDescription": {
                "translation": "Navedite lokacijo škode, če jo poznate",
                "notes": ""
            },
            "LocationTitle": {
                "translation": "Kje se škoda nahaja?",
                "notes": ""
            },
            "ObsName": {
                "translation": "Opažanje škode",
                "notes": ""
            }
        },
        "DangerObs": {
            "Area": {
                "translation": "Območje",
                "notes": ""
            },
            "Comment": {
                "translation": "Komentar",
                "notes": ""
            },
            "DangerSignTName": {
                "translation": "Vrsta nevarnosti",
                "notes": ""
            },
            "NewDangerSign": {
                "translation": "Dodaj znak nevarnosti",
                "notes": ""
            },
            "NoDamageSign": {
                "translation": "Brez znaka nevarnosti",
                "notes": ""
            },
            "ObsName": {
                "translation": "Opažanje nevarnosti",
                "notes": ""
            },
            "Title": {
                "translation": "Znak nevarnosti",
                "notes": ""
            }
        },
        "GeneralObservation": {
            "Comment": {
                "translation": "Komentar",
                "notes": ""
            },
            "NoObservationsFound": {
                "translation": "Najdeno ni bilo nobeno opažanje",
                "notes": ""
            },
            "Notes": {
                "translation": "Opombe",
                "notes": ""
            },
            "NotesForObservation": {
                "translation": "Opombe pri opažanju",
                "notes": ""
            },
            "ObsComment": {
                "translation": "Besedilo",
                "notes": ""
            },
            "ObsHeader": {
                "translation": "Naslov",
                "notes": ""
            },
            "ObsName": {
                "translation": "Splošno opažanje",
                "notes": ""
            },
            "Urls": {
                "translation": "Povezave",
                "notes": ""
            }
        },
        "IceCoverObs": {
            "BearingStrength": {
                "translation": "Nosilnost",
                "notes": ""
            },
            "Comment": {
                "translation": "Komentar",
                "notes": ""
            },
            "Description": {
                "translation": "Opis",
                "notes": ""
            },
            "IceCapacityTName": {
                "translation": "Nosilnost",
                "notes": ""
            },
            "IceCover": {
                "translation": "Ledena površina",
                "notes": ""
            },
            "IceCoverAfterTName": {
                "translation": "Prekritost z ledom po opažanju",
                "notes": ""
            },
            "IceCoverBeforeObservation": {
                "translation": "Ledena površina pred opažanjem",
                "notes": ""
            },
            "IceCoverBeforeTName": {
                "translation": "Prekritost z ledom pred opažanjem",
                "notes": ""
            },
            "IceCoverTName": {
                "translation": "Prekritost",
                "notes": ""
            },
            "IceSkateabilityTName": {
                "translation": "Možnost drsanja",
                "notes": ""
            },
            "ObsName": {
                "translation": "Opažanje ledene površine",
                "notes": ""
            }
        },
        "IceThickness": {
            "AddIceLayer": {
                "translation": "Dodaj plast ledu",
                "notes": ""
            },
            "AddIceThicknessLayer": {
                "translation": "Dodaj plast ledu",
                "notes": ""
            },
            "Comment": {
                "translation": "Komentar",
                "notes": ""
            },
            "IceHeightAfterInput": {
                "translation": "Debelina površinske vode (cm)",
                "notes": ""
            },
            "IceHeightAfterInputNo": {
                "translation": "Globina od površja do vode v luknji (cm)",
                "notes": ""
            },
            "IceHeightBeforeInput": {
                "translation": "Debelina površinske vode (cm)",
                "notes": ""
            },
            "IceLayer": {
                "translation": "Plast ledu",
                "notes": ""
            },
            "IceLayerThickness": {
                "translation": "Debelina plasti ledu (cm)",
                "notes": ""
            },
            "IceThicknessLayers": {
                "translation": "Plasti (od vrha navzdol)",
                "notes": ""
            },
            "IceThicknessSum": {
                "translation": "Skupna debelina (cm)",
                "notes": ""
            },
            "IceType": {
                "translation": "Vrsta ledu",
                "notes": ""
            },
            "IsEqualToIceSurface": {
                "translation": "enako visoko kot ledena površina",
                "notes": ""
            },
            "LowerThanIceSurface": {
                "translation": "nižje od ledene površine ",
                "notes": ""
            },
            "ObsName": {
                "translation": "Debelina ledu",
                "notes": ""
            },
            "OverIce": {
                "translation": "Nad ledom",
                "notes": ""
            },
            "OverWaterAfterDrilling": {
                "translation": "nad vodo po vrtanju",
                "notes": ""
            },
            "OverWaterBeforeDrilling": {
                "translation": "površinske vode pred vrtanjem",
                "notes": ""
            },
            "SlushSnowBeforeDrilling": {
                "translation": "Snežna brozga pred vrtanjem (cm)",
                "notes": ""
            },
            "SnowDepthBeforeDrilling": {
                "translation": "Sneg pred vrtanjem (cm)",
                "notes": ""
            },
            "Total": {
                "translation": " skupaj",
                "notes": ""
            },
            "TwoDecimalPlaces": {
                "translation": "(cm, do dve decimalni mesti)",
                "notes": ""
            },
            "WaterSurfaceInHole": {
                "translation": "Višina vode v luknji",
                "notes": ""
            }
        },
        "Incident": {
            "ActivityInfluencedTID": {
                "translation": "Dejavnost",
                "notes": ""
            },
            "Comment": {
                "translation": "Opis",
                "notes": ""
            },
            "DamageExtentTID": {
                "translation": "Obseg škode",
                "notes": ""
            },
            "Description": {
                "translation": "Zakaj se je to zgodilo? Se je dobro končalo? Se bi bilo situaciji mogoče izogniti?",
                "notes": ""
            },
            "GeoHazardTID": {
                "translation": "Vrsta opažanja",
                "notes": ""
            },
            "IncidentHeader": {
                "translation": "Naslov",
                "notes": ""
            },
            "IncidentIngress": {
                "translation": "Vstop",
                "notes": ""
            },
            "IncidentText": {
                "translation": "Opis",
                "notes": ""
            },
            "ObsName": {
                "translation": "Nesreča/dogodek",
                "notes": ""
            },
            "Urls": {
                "translation": "Povezave",
                "notes": ""
            }
        },
        "InCm": {
            "translation": "V centimetrih",
            "notes": ""
        },
        "InMeter": {
            "translation": "V metrih",
            "notes": ""
        },
        "LandslideObs": {
            "ActivityInfluencedTName": {
                "translation": "Kaj je bilo poškodovano?",
                "notes": ""
            },
            "And": {
                "translation": " in ",
                "notes": ""
            },
            "AvalTrigger": {
                "translation": "Sprožilec plazu",
                "notes": ""
            },
            "Between": {
                "translation": "Med",
                "notes": ""
            },
            "Comment": {
                "translation": "Komentar",
                "notes": ""
            },
            "DamageExtent": {
                "translation": "Obseg škode",
                "notes": ""
            },
            "DamageExtentTName": {
                "translation": "Obseg škode",
                "notes": ""
            },
            "DtLandSlideTime": {
                "translation": "Kdaj se je plaz sprožil?",
                "notes": ""
            },
            "DtLandSlideTimeEnd": {
                "translation": "Kdaj se je plaz ustavil?",
                "notes": ""
            },
            "ForecastAccurateTName": {
                "translation": "Je bila napoved ustrezna?",
                "notes": ""
            },
            "InMap": {
                "translation": "na zemljevidu",
                "notes": ""
            },
            "LandSlideSizeTName": {
                "translation": "Velikost",
                "notes": ""
            },
            "LandslideTime": {
                "translation": "Čas plazu",
                "notes": ""
            },
            "LandSlideTName": {
                "translation": "Vrsta zemeljskega plazu",
                "notes": ""
            },
            "LandSlideTriggerTName": {
                "translation": "Sprožilec",
                "notes": ""
            },
            "LandslideType": {
                "translation": "Tip plazu",
                "notes": ""
            },
            "ObsName": {
                "translation": "Opažanje zemeljskega plazu",
                "notes": ""
            },
            "Position": {
                "translation": "Lokacija plazu",
                "notes": ""
            },
            "PositionDescription": {
                "translation": "Če ju poznate, določite začetno in končno točko plazu.",
                "notes": ""
            },
            "Required": {
                "translation": "Obvezno",
                "notes": ""
            },
            "SetLandslidePosition": {
                "translation": "Določite lokacijo plazu",
                "notes": ""
            },
            "SetStartPosition": {
                "translation": "Določite začetno točko",
                "notes": ""
            },
            "SetStopPosition": {
                "translation": "Določite končno točko",
                "notes": ""
            },
            "Time": {
                "translation": "Čas",
                "notes": ""
            },
            "TimeDescription": {
                "translation": "Vnesite čas sprožitve zemeljskega plazu. Uporabite lokalni čas na mestu opažanja.",
                "notes": ""
            },
            "Title": {
                "translation": "Zemeljski plaz",
                "notes": ""
            },
            "Urls": {
                "translation": "Povezave",
                "notes": ""
            }
        },
        "Picture": {
            "Aspect": {
                "translation": "Orientacija",
                "notes": ""
            },
            "Comment": {
                "translation": "Komentar",
                "notes": ""
            },
            "Copyright": {
                "translation": "Avtorske pravice",
                "notes": ""
            },
            "Edit": {
                "translation": "Uredi sliko",
                "notes": ""
            },
            "ObsName": {
                "translation": "Slika",
                "notes": ""
            },
            "Photographer": {
                "translation": "Fotograf",
                "notes": ""
            },
            "PictureComment": {
                "translation": "Komentar",
                "notes": ""
            },
            "RegistrationTID": {
                "translation": "Slika od",
                "notes": ""
            }
        },
        "Shared": {
            "Description": {
                "translation": "Opis",
                "notes": ""
            },
            "ExposedHeight": {
                "Height": {
                    "translation": "Višina",
                    "notes": ""
                },
                "LowerHeight": {
                    "translation": "Spodnja višina",
                    "notes": ""
                },
                "Title": {
                    "translation": "Izpostavljena višina",
                    "notes": ""
                }
            },
            "UnsentDescription": {
                "translation": "Obrazec ni shranjen v Regobs.",
                "notes": ""
            },
            "UnsentSummaryTitle": {
                "translation": "Neoddani obrazec",
                "notes": ""
            },
            "ValidExposition": {
                "All": {
                    "translation": "Vse",
                    "notes": ""
                },
                "Title": {
                    "translation": "Usmerjenost pobočja",
                    "notes": ""
                }
            }
        },
        "SnowCover": {
            "CriticalLayer": {
                "translation": "Šibka plast",
                "notes": ""
            },
            "CriticalLayerFound": {
                "translation": "Obstaja šibka plast.",
                "notes": ""
            },
            "CriticalLayerLocation": {
                "translation": "Lokacija",
                "notes": ""
            },
            "CriticalLayerNotFound": {
                "translation": "Šibka plast ne obstaja.",
                "notes": ""
            },
            "CriticalLayerTID": {
                "translation": "Vrsta",
                "notes": ""
            },
            "DepthHoar": {
                "translation": "Globinski srež",
                "notes": ""
            },
            "DepthHoarInSnowCover": {
                "translation": "opažen globinski srež.",
                "notes": ""
            },
            "ObsName": {
                "translation": "Snežni profil",
                "notes": ""
            },
            "SnowPilotRefTID": {
                "translation": "Snežni profil",
                "notes": ""
            },
            "UnderSurface": {
                "translation": "pod površino",
                "notes": ""
            }
        },
        "SnowProfile": {
            "AddLayerBottom": {
                "translation": "Dodaj novo plast na dnu",
                "notes": ""
            },
            "AddLayers": {
                "translation": "Dodaj plasti",
                "notes": ""
            },
            "AddLayerTop": {
                "translation": "Dodaj novo plast na vrhu",
                "notes": ""
            },
            "AddTests": {
                "translation": "Dodaj teste",
                "notes": ""
            },
            "Cm": {
                "translation": "cm",
                "notes": ""
            },
            "Comment": {
                "translation": "Komentar",
                "notes": ""
            },
            "CompressionTest": {
                "translation": "Tlačni testi",
                "notes": ""
            },
            "CompresstionTestConnectedToProfile": {
                "translation": "tlačni testi povezani s snežnim profilom",
                "notes": ""
            },
            "Density": {
                "AddDensity": {
                    "translation": "Dodaj gostoto",
                    "notes": ""
                },
                "Average": {
                    "translation": "Povprečje",
                    "notes": ""
                },
                "CylinderBoreDiam": {
                    "translation": "Premer valja (cm)",
                    "notes": ""
                },
                "Density": {
                    "translation": "Gostota",
                    "notes": ""
                },
                "DensityLabel": {
                    "translation": "Gostota (kg/m3)",
                    "notes": ""
                },
                "DensityProfileAdded": {
                    "translation": "dodan profil gostote",
                    "notes": ""
                },
                "DensityProfiles": {
                    "translation": "profili gostote",
                    "notes": ""
                },
                "Height": {
                    "translation": "Višina (cm)",
                    "notes": ""
                },
                "Layer": {
                    "translation": "Plast",
                    "notes": ""
                },
                "Method": {
                    "translation": "Metoda",
                    "notes": ""
                },
                "Sum": {
                    "translation": "Vsota",
                    "notes": ""
                },
                "Summary": {
                    "translation": "Povzetek",
                    "notes": ""
                },
                "TareWeight": {
                    "translation": "Teža valja in vrečke (g)",
                    "notes": ""
                },
                "UseCylinder": {
                    "translation": "Uporabi valj",
                    "notes": ""
                },
                "WaterEquivalent": {
                    "translation": "Vodni ekvivalent (mm)",
                    "notes": ""
                },
                "Weight": {
                    "translation": "Teža (g)",
                    "notes": ""
                }
            },
            "DepthPlaceholder": {
                "translation": "Globina (cm)",
                "notes": ""
            },
            "IsProfileDugToTheGround": {
                "translation": "Je snežni profil izkopan do tal?",
                "notes": ""
            },
            "Layers": {
                "translation": "Plasti",
                "notes": ""
            },
            "LayersObserved": {
                "translation": "opažene plasti",
                "notes": ""
            },
            "Main": {
                "translation": "Splošno",
                "notes": ""
            },
            "ObsName": {
                "translation": "Snežni profil",
                "notes": ""
            },
            "SnowDensity": {
                "translation": "Gostota snega",
                "notes": ""
            },
            "SnowTemperature": {
                "translation": "Temperatura",
                "notes": ""
            },
            "Stratification": {
                "CriticalLayer": {
                    "translation": "Kritična plast",
                    "notes": ""
                },
                "DeleteLayer": {
                    "translation": "Izbriši plast",
                    "notes": ""
                },
                "GetLayers": {
                    "translation": "Pridobi plasti iz drugih profilov",
                    "notes": ""
                },
                "GetLayersFromOtherObsInfo": {
                    "translation": "Lahko kopirate plast iz katerega izmed prejšnjih profilov, ki je bil vnešen v preteklih 14 dneh v radiju 100 km.",
                    "notes": ""
                },
                "GrainFormPrimary": {
                    "translation": "0blika kristalov",
                    "notes": ""
                },
                "GrainFormSecondary": {
                    "translation": "Sekundarna oblika kristalov",
                    "notes": ""
                },
                "GrainSizeAvg": {
                    "translation": "Velikost kristalov (mm)",
                    "notes": ""
                },
                "GrainSizeAvgMax": {
                    "translation": "Največja velikost kristalov (mm)",
                    "notes": ""
                },
                "Hardness": {
                    "translation": "Trdnost",
                    "notes": ""
                },
                "HardnessBottom": {
                    "translation": "Trdnost na dnu",
                    "notes": ""
                },
                "Layer": {
                    "translation": "Plast",
                    "notes": ""
                },
                "MultipleObserved": {
                    "translation": "plasti",
                    "notes": ""
                },
                "NoPreviousLayersFound": {
                    "translation": "Ni najdenih plasti iz drugih profilov",
                    "notes": ""
                },
                "Observed": {
                    "translation": "plast",
                    "notes": ""
                },
                "SelectLayers": {
                    "translation": "Izberi plasti",
                    "notes": ""
                },
                "ShowLess": {
                    "translation": "Pokaži manj možnosti",
                    "notes": ""
                },
                "ShowMore": {
                    "translation": "Pokaži več možnosti",
                    "notes": ""
                },
                "Thickness": {
                    "translation": "Debelina (mm)",
                    "notes": ""
                },
                "UseLayers": {
                    "translation": "Uporabi plasti",
                    "notes": ""
                },
                "Wetness": {
                    "translation": "Vodnatost",
                    "notes": ""
                }
            },
            "StratLayers": {
                "translation": "Plasti",
                "notes": ""
            },
            "SumOfAllLayers": {
                "translation": "Vsota vseh plasti:",
                "notes": ""
            },
            "Temperature": {
                "Add": {
                    "translation": "Dodaj temperaturo",
                    "notes": ""
                },
                "MultipleObserved": {
                    "translation": "izmerjene temperature v točkah",
                    "notes": ""
                },
                "Observed": {
                    "translation": "izmerjena temperatura v točki",
                    "notes": ""
                },
                "Placeholder": {
                    "translation": "Temperatura (°C)",
                    "notes": ""
                },
                "TempProfile": {
                    "translation": "Temperaturni profil",
                    "notes": ""
                }
            },
            "Test": {
                "Add": {
                    "translation": "Dodaj",
                    "notes": ""
                },
                "AddTest": {
                    "translation": "Dodaj test",
                    "notes": ""
                },
                "AttachedToProfile": {
                    "translation": "testi, povezani s profilom",
                    "notes": ""
                },
                "AttachedToProfileTooltip": {
                    "translation": "Test je povezan s snežnim profilom",
                    "notes": ""
                },
                "Tests": {
                    "translation": "testi",
                    "notes": ""
                },
                "TestsWillAppearHere": {
                    "translation": "Testi, ki ste jih dodali, se bodo pojavili tukaj",
                    "notes": ""
                },
                "Update": {
                    "translation": "Posodobi test",
                    "notes": ""
                }
            }
        },
        "SnowSurfaceObservation": {
            "Comment": {
                "translation": "Komentar",
                "notes": ""
            },
            "CommentHeader": {
                "translation": "Opišite snežno odejo",
                "notes": ""
            },
            "CommentPlaceholder": {
                "translation": "Kakšna je na splošno porazdelitev snega glede na višino in usmerjenost pobočij? Ali so opazne velike razlike na območju?",
                "notes": ""
            },
            "FootPenetration": {
                "translation": "Ugrez pri hoji",
                "notes": ""
            },
            "HeightLimitLayeredSnow": {
                "translation": "Višina, kjer se začne sneg v plasteh (m.n.v.)",
                "notes": ""
            },
            "HightLimitLayeredSnowPlaceholder": {
                "translation": "Za snežno odejo brez nevarnih plasti",
                "notes": ""
            },
            "NewSnow": {
                "translation": "nov sneg",
                "notes": ""
            },
            "NewSnowDepth24": {
                "translation": "Nov sneg v zadnjih 24 urah (cm)",
                "notes": ""
            },
            "NewSnowLine": {
                "translation": "Meja novega snega (m.n.v.)",
                "notes": ""
            },
            "ObsName": {
                "translation": "Snežna odeja",
                "notes": ""
            },
            "SnowDepth": {
                "translation": "Višina snežne odeje (cm)",
                "notes": ""
            },
            "SnowDriftTName": {
                "translation": "Napihan sneg",
                "notes": ""
            },
            "SnowLine": {
                "translation": "Meja snega (m.n.v.)",
                "notes": ""
            },
            "SnowLines": {
                "translation": "Meje snega",
                "notes": ""
            },
            "SnowSurfaceTName": {
                "translation": "Snežna odeja",
                "notes": ""
            },
            "SurfaceRougnessTName": {
                "translation": "Hrapavost površine",
                "notes": ""
            },
            "SurfaceWaterContentTName": {
                "translation": "Vlažnost snežne odeje",
                "notes": ""
            },
            "Total": {
                "translation": "skupaj",
                "notes": ""
            }
        },
        "WaterLevel": {
            "AppliesFor": {
                "translation": "Nanaša se na",
                "notes": ""
            },
            "Comment": {
                "translation": "Komentar",
                "notes": ""
            },
            "Lake": {
                "translation": "jezero",
                "notes": ""
            },
            "MeasuredDischarge": {
                "translation": "Izmerjen pretok",
                "notes": ""
            },
            "ObsName": {
                "translation": "Nivo vode",
                "notes": ""
            },
            "River": {
                "translation": "reko",
                "notes": ""
            },
            "WaterLevelDescribed": {
                "translation": "Opis nivoja vode",
                "notes": ""
            },
            "WaterLevelRefTName": {
                "translation": "Meritev vodnega nivoja glede na",
                "notes": ""
            },
            "WaterLevelValue": {
                "translation": "Vrednost",
                "notes": ""
            }
        },
        "WaterLevel2": {
            "AddNewMarking": {
                "translation": "Dodajte novo označevanje vodostaja",
                "notes": ""
            },
            "AddNewMeasurement": {
                "translation": "Dodajte novo meritev vodostaja",
                "notes": ""
            },
            "Comment": {
                "translation": "Komentar",
                "notes": ""
            },
            "DescribeSituationQuestion": {
                "translation": "Kako bi opisali situacijo?",
                "notes": ""
            },
            "MarkingComment": {
                "translation": "Opišite oznako",
                "notes": ""
            },
            "MarkingReferenceQuestion": {
                "translation": "Vodostaj sem označil na",
                "notes": ""
            },
            "MarkingTypeQuestion": {
                "translation": "Vodostaj sem označil z",
                "notes": ""
            },
            "MeasuredRelativeTo": {
                "translation": "Meritev glede na",
                "notes": ""
            },
            "MeasurementComment": {
                "translation": "Opišite meritev",
                "notes": ""
            },
            "MeasurementReferenceComment": {
                "translation": "Opišite vodostaj",
                "notes": ""
            },
            "MeasurementReferenceQuestion": {
                "translation": "Vodostaj je relativen glede na",
                "notes": ""
            },
            "MeasurementReferenceTName": {
                "translation": "Vodna oznaka na/z",
                "notes": ""
            },
            "MeasurementTypeQuestion": {
                "translation": "Na kakšen način določate vodostaj?",
                "notes": ""
            },
            "MeasurementTypeTName": {
                "translation": "Merilni inštrument",
                "notes": ""
            },
            "MeasuringToolDescription": {
                "translation": "Vnesite merilni inštrument / pripomoček",
                "notes": ""
            },
            "ObservationTimingQuestion": {
                "translation": "Kaj opazujete?",
                "notes": ""
            },
            "ObservationTimingTName": {
                "translation": "Kaj vnašate?",
                "notes": ""
            },
            "ObsName": {
                "translation": "Nivo vode",
                "notes": ""
            },
            "WaterAstrayQuestion": {
                "translation": "Je kaj vode izven struge?",
                "notes": ""
            },
            "WaterAstrayTName": {
                "translation": "Je kaj vode izven struge?",
                "notes": ""
            },
            "WaterLevelDescription": {
                "translation": "Vodostaj v metrih",
                "notes": ""
            },
            "WaterLevelMethodQuestion": {
                "translation": "Kako opazujete?",
                "notes": ""
            },
            "WaterLevelStateTName": {
                "translation": "Stanje",
                "notes": ""
            },
            "WaterMarking": {
                "translation": "Vodna oznaka",
                "notes": ""
            },
            "WaterMeasurement": {
                "translation": "Meritev vode",
                "notes": ""
            },
            "WaterMeasurementValue": {
                "translation": "Vrednost meritve vode",
                "notes": ""
            },
            "With": {
                "translation": "z",
                "notes": ""
            }
        },
        "WeatherObservation": {
            "AirTemperature": {
                "translation": "Temperatura zraka (°C)",
                "notes": ""
            },
            "AirTemperaturePlaceholder": {
                "translation": "Lahko se vnese z dvema decimalkama",
                "notes": ""
            },
            "CloudCover": {
                "translation": "Oblačnost (%)",
                "notes": ""
            },
            "Clouds": {
                "translation": "oblaki",
                "notes": ""
            },
            "Comment": {
                "translation": "Komentar",
                "notes": ""
            },
            "CommentHeader": {
                "translation": "Opišite vreme",
                "notes": ""
            },
            "CommentPlaceholder": {
                "translation": "Kakšno je bilo vreme v preteklih 24 urah? Primer: Je padal sneg? Je bilo opaziti spremembe v temperaturi? Na kateri višini poteka ničelna izoterma?",
                "notes": ""
            },
            "FromEast": {
                "translation": "V - iz vzhoda",
                "notes": ""
            },
            "FromNorth": {
                "translation": "S - iz severa",
                "notes": ""
            },
            "FromNorthEast": {
                "translation": "SV - iz severovzhoda",
                "notes": ""
            },
            "FromNorthWest": {
                "translation": "SZ - iz severozahoda",
                "notes": ""
            },
            "FromSouth": {
                "translation": "J - iz juga",
                "notes": ""
            },
            "FromSouthEast": {
                "translation": "JV - iz jugovzhoda",
                "notes": ""
            },
            "FromSouthWest": {
                "translation": "JZ - iz jugozahoda",
                "notes": ""
            },
            "FromWest": {
                "translation": "Z - iz zahoda",
                "notes": ""
            },
            "ObsName": {
                "translation": "Vremensko opažanje",
                "notes": ""
            },
            "OnlyFullPercentage": {
                "translation": "Odstotki brez decimalk",
                "notes": ""
            },
            "Precipitation": {
                "translation": "Padavine",
                "notes": ""
            },
            "PrecipitationTID": {
                "translation": "Tip padavin",
                "notes": ""
            },
            "Wind": {
                "translation": "Vetrovne razmere",
                "notes": ""
            },
            "WindDirection": {
                "translation": "Smer vetra",
                "notes": ""
            },
            "WindSpeed": {
                "translation": "Hitrost vetra (m/s)",
                "notes": ""
            }
        }
    },
    "Of": {
        "translation": "od",
        "notes": ""
    },
    "Ok": {
        "translation": "Ok",
        "notes": ""
    },
    "Password": {
        "translation": "Geslo",
        "notes": ""
    },
    "picture": {
        "translation": "slika",
        "notes": ""
    },
    "PictureCarousel": {
        "Comment": {
            "translation": "Komentar",
            "notes": ""
        },
        "Copyright": {
            "translation": "Avtorske pravice",
            "notes": ""
        },
        "Image": {
            "translation": "Slika",
            "notes": ""
        },
        "ObservedLocation": {
            "translation": "Opažena lokacija",
            "notes": ""
        },
        "Of": {
            "translation": "od",
            "notes": ""
        }
    },
    "PictureKey": {
        "translation": "Slika",
        "notes": ""
    },
    "PictureMode": {
        "translation": "Slike",
        "notes": ""
    },
    "Reg": {
        "ObservedTime": {
            "translation": "Opaženo",
            "notes": ""
        },
        "ObserverNickName": {
            "translation": "Uporabniško ime",
            "notes": ""
        },
        "RegisteredTime": {
            "translation": "Vnešeno",
            "notes": ""
        },
        "UpdatedTime": {
            "translation": "Posodobljeno",
            "notes": ""
        }
    },
    "Register": {
        "translation": "Registracija novega uporabnika",
        "notes": ""
    },
    "RegistrationDetail": {
        "EditInfo": {
            "translation": "Svoja opažanja ali opažanja skupine, ki ji pripadate, lahko urejate 48 ur po vnosu.",
            "notes": ""
        }
    },
    "RegistrationEdit": {
        "AddForm": {
            "translation": "Dodaj obrazec",
            "notes": ""
        },
        "BadRequest": {
            "translation": "Nepravilen zahtevek",
            "notes": ""
        },
        "ConfirmDelete": {
            "translation": "Ali ste prepričani, da želite izbrisati to opažanje?",
            "notes": ""
        },
        "ContinueOnDraft": {
            "translation": "Nadaljujte z osnutkom",
            "notes": ""
        },
        "ContinueOnDraftButton": {
            "translation": "Nadaljuj z osnutkom",
            "notes": ""
        },
        "ContinueOnDraftCancelButton": {
            "translation": "Novo opažanje",
            "notes": ""
        },
        "ContinueOnDraftMessage": {
            "translation": "Imate osnutek iz",
            "notes": ""
        },
        "ContinueOnDraftQuestion": {
            "translation": "Ali želite nadaljevati s tem osnutkom?",
            "notes": ""
        },
        "DeleteError": {
            "translation": "Opažanja ni bilo mogoče izbrisati!",
            "notes": ""
        },
        "DeleteObservation": {
            "translation": "Izbriši opažanje",
            "notes": ""
        },
        "Discard": {
            "translation": "Zavrzi",
            "notes": ""
        },
        "Done": {
            "translation": "Končano",
            "notes": ""
        },
        "ErrorHasBeenLogged": {
            "translation": "Sporočilo o napaki je bilo zabeleženo v sistemu z referenčnim ID-jem",
            "notes": ""
        },
        "FormInfo": {
            "translation": "Izpolnite obrazce, ki ustrezajo vrsti opažanja, ki ste ga opazili. Dodati morate vsaj en obrazec za opažanje, ki ga želite zabeležiti.",
            "notes": ""
        },
        "MissingNetwork": {
            "translation": "Ni povezave z omrežjem ali pa je povezava potekla. Čez nekaj časa bomo ponovno poskusili in upali, da se je povezava izboljšala.",
            "notes": ""
        },
        "NoCancel": {
            "translation": "Ne, prekliči",
            "notes": ""
        },
        "Retry": {
            "translation": "Poskusite znova",
            "notes": ""
        },
        "SaveAsDraft": {
            "translation": "Shraniti kot osnutek?",
            "notes": ""
        },
        "SaveDraft": {
            "translation": "Shrani osnutek",
            "notes": ""
        },
        "SaveDraftMessage": {
            "translation": "Niste dodali nobenih obrazcev in zato opažanja ne bomo objavili. Ali boste shranili kot osnutek in nadaljevali pozneje?",
            "notes": ""
        },
        "SubmitFailedHeader": {
            "translation": "Neuspešna oddaja",
            "notes": ""
        },
        "SyncError": {
            "translation": "Opažanja ni bilo mogoče sinhronizirati z Regobsom!",
            "notes": ""
        },
        "SyncErrorFormInfo": {
            "translation": "Enega ali več predmetov v tem obrazcu ni bilo mogoče oddati.",
            "notes": ""
        },
        "SyncInProgress": {
            "translation": "Sinhronizacija v teku:",
            "notes": ""
        },
        "YesDelete": {
            "translation": "Da, izbriši!",
            "notes": ""
        }
    },
    "RegistrationKeyInfo": {
        "Accuracy": {
            "translation": "Natančnost",
            "notes": ""
        },
        "Edit": {
            "translation": "Uredi",
            "notes": ""
        },
        "MetersAboveSeaLevel": {
            "translation": "Nadmorska višina",
            "notes": ""
        },
        "Municipal": {
            "translation": "Občina",
            "notes": ""
        },
        "Source": {
            "translation": "Vir",
            "notes": ""
        },
        "WarningRegion": {
            "translation": "Območje opozorila",
            "notes": ""
        }
    },
    "RememberMe": {
        "translation": "Zapomni si me",
        "notes": ""
    },
    "RequiredField": {
        "translation": "*Obvezno polje",
        "notes": ""
    },
    "RequiredFieldError": {
        "translation": "To polje je obvezno",
        "notes": ""
    },
    "Reset": {
        "translation": "Ponastavi",
        "notes": ""
    },
    "Routes": {
        "About": {
            "translation": "O",
            "notes": ""
        },
        "Cookies": {
            "translation": "Piškotki",
            "notes": ""
        },
        "Home": {
            "translation": "Domov",
            "notes": ""
        }
    },
    "Save": {
        "translation": "Shrani",
        "notes": ""
    },
    "Search": {
        "Criterias": {
            "Area": {
                "Label": {
                    "translation": "Območja",
                    "notes": ""
                },
                "List": {
                    "translation": "Območja",
                    "notes": ""
                },
                "Norway": {
                    "translation": "Norveška",
                    "notes": ""
                },
                "Search": {
                    "translation": "V bližini",
                    "notes": ""
                }
            },
            "Country": {
                "Label": {
                    "translation": "Druge države",
                    "notes": ""
                }
            },
            "FreeText": {
                "Label": {
                    "translation": "Besedilo v opažanju",
                    "notes": ""
                },
                "Placeholder": {
                    "translation": "Išči besedilo",
                    "notes": ""
                }
            },
            "ObservationType": {
                "Label": {
                    "translation": "Vrste opažanj",
                    "notes": ""
                }
            },
            "Observers": {
                "CompetenceFilter": {
                    "translation": "Usposobljenost",
                    "notes": ""
                },
                "CompetenceLevelExplanation": {
                    "translation": "Razlaga stopnje usposobljenosti",
                    "notes": ""
                },
                "Label": {
                    "translation": "Opazovalci",
                    "notes": ""
                },
                "MyObservations": {
                    "translation": "Moja opažanja",
                    "notes": ""
                },
                "ObserverNickNamePlaceholder": {
                    "translation": "Iskanje po uporabniškem imenu opazovalca",
                    "notes": ""
                },
                "SearchInCompetences": {
                    "translation": "Išči po usposobljenosti opazovalca: ",
                    "notes": ""
                },
                "SearchNickName": {
                    "translation": "Iskanje po uporabniškegem imenu",
                    "notes": ""
                }
            },
            "QuickSearch": {
                "Label": {
                    "translation": "Hitro iskanje",
                    "notes": ""
                }
            },
            "Recent": {
                "Day": {
                    "translation": "dnevi",
                    "notes": ""
                },
                "FromDate": {
                    "translation": "Od",
                    "notes": ""
                },
                "Label": {
                    "translation": "Moja zadnja iskanja",
                    "notes": ""
                },
                "Last": {
                    "translation": "Zadnji",
                    "notes": ""
                },
                "MyObservations": {
                    "translation": "Moja opažanja",
                    "notes": ""
                },
                "ObserverCompetence": {
                    "translation": "Usposobljenost opazovalca",
                    "notes": ""
                },
                "ObserverName": {
                    "translation": "Ime opazovalca",
                    "notes": ""
                },
                "Regions": {
                    "translation": "Območja",
                    "notes": ""
                },
                "RegistrationTypes": {
                    "translation": "Vrste opažanj",
                    "notes": ""
                },
                "Time": {
                    "translation": "Časovno obdobje",
                    "notes": ""
                },
                "ToDate": {
                    "translation": "Do",
                    "notes": ""
                }
            },
            "Regions": {
                "BRegionInfo": {
                    "translation": "* Napovedi so izdane samo ob stopnji nevarnosti 4 ali 5",
                    "notes": ""
                },
                "Label": {
                    "translation": "Opozorilna območja",
                    "notes": ""
                }
            },
            "TimePeriod": {
                "ChooseDate": {
                    "translation": "izberi datum",
                    "notes": ""
                },
                "Day": {
                    "translation": "dan",
                    "notes": ""
                },
                "Days": {
                    "translation": "dni",
                    "notes": ""
                },
                "FilterByDays": {
                    "translation": "Pokaži zadnjih: ",
                    "notes": ""
                },
                "FromDate": {
                    "translation": "Od",
                    "notes": ""
                },
                "FromDatePicker": {
                    "Placeholder": {
                        "translation": "izberi začetni datum",
                        "notes": ""
                    }
                },
                "InvalidDate": {
                    "translation": "Neveljaven datum",
                    "notes": ""
                },
                "InvalidDateRange": {
                    "translation": "Neveljavno časovno obdobje",
                    "notes": ""
                },
                "InvalidInteger": {
                    "translation": "Neveljavno število",
                    "notes": ""
                },
                "Label": {
                    "translation": "Časovno obdobje",
                    "notes": ""
                },
                "Last": {
                    "translation": "Zadnjih",
                    "notes": ""
                },
                "NumberOfDays": {
                    "Placeholder": {
                        "translation": "Število dni",
                        "notes": ""
                    }
                },
                "Or": {
                    "translation": "ali",
                    "notes": ""
                },
                "OrChooseDate": {
                    "translation": "ali izberi datum",
                    "notes": ""
                },
                "OrChooseRange": {
                    "translation": "Izberi časovno obdobje",
                    "notes": ""
                },
                "ToDate": {
                    "translation": "Do",
                    "notes": ""
                },
                "ToDatePicker": {
                    "Placeholder": {
                        "translation": "izberi končni datum",
                        "notes": ""
                    }
                }
            }
        },
        "GetMoreRegistrationsBtn": {
            "translation": "Pridobi več opažanj",
            "notes": ""
        },
        "Header": {
            "HideRegTypeFilter": {
                "translation": "Skrij filter",
                "notes": ""
            },
            "ShowRegTypeFilter": {
                "translation": "Prikaži filter",
                "notes": ""
            },
            "Sort": {
                "Label": {
                    "translation": "Razvrsti po",
                    "notes": ""
                },
                "LastUpdated": {
                    "translation": "Zadnji posodobljeni čas",
                    "notes": ""
                },
                "Observed": {
                    "translation": "Čas opažanja",
                    "notes": ""
                },
                "Registered": {
                    "translation": "Čas vnosa",
                    "notes": ""
                }
            },
            "ViewMode": {
                "ListKey": {
                    "translation": "Seznam",
                    "notes": ""
                },
                "MapKey": {
                    "translation": "Zemljevid",
                    "notes": ""
                },
                "PictureKey": {
                    "translation": "Slika",
                    "notes": ""
                }
            }
        },
        "HeadingColor": {
            "black": {
                "translation": "Črna",
                "notes": ""
            },
            "blue": {
                "translation": "Modra",
                "notes": ""
            }
        },
        "LoadMoreRegistrationsText": {
            "translation": "Kliknite tu, da ročno naložite več opažanj.",
            "notes": ""
        },
        "SearchButton": {
            "translation": "Išči med opažanji",
            "notes": ""
        },
        "SearchFilters": {
            "translation": "Iskalni filtri",
            "notes": ""
        },
        "SortOrder": {
            "Observert tid": {
                "translation": "Opaženo",
                "notes": ""
            },
            "Registrert tid": {
                "translation": "Vnešeno",
                "notes": ""
            },
            "Siste oppdatert tid": {
                "translation": "Zadnjič posodobljeno",
                "notes": ""
            }
        }
    },
    "SearchButtonName": {
        "translation": "Išči",
        "notes": ""
    },
    "Searching": {
        "translation": "Iskanje, prosimo počakajte",
        "notes": ""
    },
    "SearchResultOfTotal": {
        "translation": "od",
        "notes": ""
    },
    "ShowAllObservations": {
        "translation": "Pokaži vsa opažanja",
        "notes": ""
    },
    "ShowFilteredObservations": {
        "translation": "Pokaži samo izbrana opažanja",
        "notes": ""
    },
    "ShowLess": {
        "translation": "Pokaži manj",
        "notes": ""
    },
    "ShowMore": {
        "translation": "Pokaži več",
        "notes": ""
    },
    "ShowSearchButtonName": {
        "translation": "Prikaži iskalnik",
        "notes": ""
    },
    "SignIn": {
        "translation": "Prijava",
        "notes": ""
    },
    "SignOut": {
        "translation": "Odjava",
        "notes": ""
    },
    "SingleRegistration": {
        "translation": "vnos",
        "notes": ""
    },
    "snø": {
        "translation": "snega",
        "notes": ""
    },
    "SortByName": {
        "translation": "Razvrsti po:",
        "notes": ""
    },
    "TableModes": {
        "CompactKey": {
            "translation": "Strnjeno",
            "notes": ""
        },
        "CompleteKey": {
            "translation": "Zaključeno",
            "notes": ""
        },
        "ShortKey": {
            "translation": "Kratko",
            "notes": ""
        }
    },
    "Time": {
        "translation": "čas",
        "notes": ""
    },
    "to": {
        "translation": "do",
        "notes": ""
    },
    "Unknown": {
        "translation": "Neznano",
        "notes": ""
    },
    "Url": {
        "Add": {
            "translation": "Dodaj spletno povezavo",
            "notes": ""
        },
        "Description": {
            "translation": "Opis",
            "notes": ""
        },
        "Edit": {
            "translation": "Uredi",
            "notes": ""
        },
        "EditUrl": {
            "translation": "Uredi spletno povezavo",
            "notes": ""
        },
        "Url": {
            "translation": "URL",
            "notes": ""
        },
        "WebUrl": {
            "translation": "Spletna povezava",
            "notes": ""
        }
    },
    "UserMenu": {
        "Language": {
            "translation": "JEZIK",
            "notes": ""
        },
        "Page": {
            "translation": "STRAN",
            "notes": ""
        },
        "Regobs": {
            "translation": "REGOBS",
            "notes": ""
        },
        "User": {
            "translation": "UPORABNIK",
            "notes": ""
        }
    },
    "vann": {
        "translation": "poplava",
        "notes": ""
    },
    "Yes": {
        "translation": "Ja",
        "notes": ""
    }
}